ChatterAgent/__init__.py
ChatterAgent/__main__.py
ChatterAgent/agent.py
ChatterAgent-0.6.dist-info/METADATA
ChatterAgent-0.6.dist-info/WHEEL
ChatterAgent-0.6.dist-info/top_level.txt
ChatterAgent-0.6.dist-info/RECORD
