Metadata-Version: 2.1
Name: ChatterAgent
Version: 0.6
Summary: A Python package for spawning agents that interface with the OpenAI ChatGPT API.
Home-page: https://github.com/SevanBrodjian/ChatAgent
Author: Sevan Brodjian
Author-email: sevanbro7@gmail.com
Requires-Python: >=3.6
